softozor_test_utils/__init__.py
softozor_test_utils/sockets.py
softozor_test_utils/timing.py
softozor_test_utils-1.0.13.dist-info/METADATA
softozor_test_utils-1.0.13.dist-info/WHEEL
softozor_test_utils-1.0.13.dist-info/top_level.txt
softozor_test_utils-1.0.13.dist-info/RECORD
