Metadata-Version: 2.1
Name: softozor-test-utils
Version: 1.0.13
Summary: A test utils library for softozor projects
Home-page: https://gitlab.hidora.com/softozor/packages
Author: Laurent Michel
Author-email: softozor@gmail.com
License: UNKNOWN
Platform: UNKNOWN
Classifier: Programming Language :: Python :: 3.9
Classifier: License :: OSI Approved :: MIT License
Classifier: Operating System :: OS Independent
Requires-Python: >=3.9
Requires-Dist: sh
Provides-Extra: test
